Metadata-Version: 2.1
Name: djrestframework
Version: 5.16.0
Summary: Web APIs for Django, made easy.
Home-page: https://www.django-rest-framework.org/
Author: Mowar Lee
Author-email: leemowar@gmail.com
License: BSD
Project-URL: Source, https://github.com/mowarlee/django-rest-framework
Classifier: Development Status :: 5 - Production/Stable
Classifier: Environment :: Web Environment
Classifier: Framework :: Django
Classifier: Framework :: Django :: 4.0
Classifier: Framework :: Django :: 4.1
Classifier: Framework :: Django :: 4.2
Classifier: Intended Audience :: Developers
Classifier: License :: OSI Approved :: BSD License
Classifier: Operating System :: OS Independent
Classifier: Programming Language :: Python
Classifier: Programming Language :: Python :: 3
Classifier: Programming Language :: Python :: 3.10
Classifier: Programming Language :: Python :: 3.11
Classifier: Programming Language :: Python :: 3 :: Only
Classifier: Topic :: Internet :: WWW/HTTP
Requires-Python: >=3.10
License-File: LICENSE.md
